<system>
	<name>HD 88133</name>
	<rightascension>10 10 07</rightascension>
	<declination>+18 11 12</declination>
	<distance>74.46</distance>
	<star>
		<mass>1.2</mass>
		<radius>1.93</radius>
		<magV>8.01</magV>
		<magB>8.88</magB>
		<magR>7.5</magR>
		<magI>7.1</magI>
		<magJ>6.60</magJ>
		<magH>6.30</magH>
		<magK>6.20</magK>
		<metallicity>0.34</metallicity>
		<spectraltype>G5 IV</spectraltype>
		<planet>
			<name>HD 88133 b</name>
			<list>Confirmed planets</list>
			<mass>1.02</mass>
			<period>3.4148674</period>
			<semimajoraxis>0.04691</semimajoraxis>
			<eccentricity>0.05</eccentricity>
			<discoverymethod>RV</discoverymethod>
			<lastupdate>13/2016-10-1/2016-10-1</lastupdate>
			<discoveryyear>2004</discoveryyear>
			<temperature>1550.6</temperature>
		<periastron errorminus="-48.1100" errorplus="-48.1100">7.22</periastron><inclination errorminus="-5.000" errorplus="-5.000">15.0</inclination><periastrontime errorminus="-0.451000" errorplus="-0.451000">2454641.984</periastrontime><istransiting>0</istransiting></planet>
		<name>HD 88133</name>
		<temperature>5494.0</temperature>
	</star>
</system>